batou_ext/__init__.py
batou_ext/acl.py
batou_ext/archive.py
batou_ext/config.py
batou_ext/cron.py
batou_ext/fcio.py
batou_ext/file.py
batou_ext/geoip.py
batou_ext/git.py
batou_ext/htpasswd.py
batou_ext/http.py
batou_ext/jenkins.py
batou_ext/journalbeat.py
batou_ext/keypair.py
batou_ext/mail.py
batou_ext/mailhog.py
batou_ext/memcached.py
batou_ext/mirror.py
batou_ext/mysql.py
batou_ext/nfs.py
batou_ext/nix.py
batou_ext/nixos.py
batou_ext/oci.py
batou_ext/php.py
batou_ext/postgres.py
batou_ext/python.py
batou_ext/rabbitmq.py
batou_ext/redis.py
batou_ext/run.py
batou_ext/s3.py
batou_ext/s3_bootstrap.py
batou_ext/ssh.py
batou_ext/ssl.py
batou_ext/systemd.py
batou_ext/versions.py
batou_ext/postfixadmin/__init__.py
batou_ext/postfixadmin/dovecot.py
batou_ext/postfixadmin/goceptnet.py
batou_ext/postfixadmin/postfix.py
batou_ext/postfixadmin/postgres.py
batou_ext/postfixadmin/dovecot/database.conf
batou_ext/postfixadmin/dovecot/local.conf
batou_ext/postfixadmin/postfix/local.cf
batou_ext/postfixadmin/postfix/postfixadmin_virtual_alias
batou_ext/postfixadmin/postfix/postfixadmin_virtual_domains
batou_ext/postfixadmin/postfix/postfixadmin_virtual_mailboxes
batou_ext/postfixadmin/postfix/postfixadmin_virtual_sender_login
batou_ext/postfixadmin/postfixadmin/config.local.php
batou_ext/resources/cert.sh
batou_ext/resources/check_systemd_unit.py
batou_ext/resources/cron-wrapper.sh
batou_ext/resources/geoip-update.sh
batou_ext/resources/http-watchdog.nix
batou_ext/resources/journalbeat.nix
batou_ext/resources/loader.c
batou_ext/resources/mailpit.nix
batou_ext/resources/mirror.conf
batou_ext/resources/oci-template.nix
batou_ext/resources/python.nix
batou_ext/resources/rediscleanup.sh
batou_ext/resources/scalable-service.nix
batou_ext/resources/setupEnv.sh
batou_ext/resources/systemd.service
batou_ext/resources/userenv.nix
batou_ext/resources/watchdog-wrapper.py
batou_ext/resources/mailhog/mailhog.nix
batou_ext/resources/php/php-fpm.conf
batou_ext/resources/php/php-fpm.sh
batou_ext-2.4.35.dist-info/licenses/LICENSE.txt
batou_ext-2.4.35.dist-info/METADATA
batou_ext-2.4.35.dist-info/WHEEL
batou_ext-2.4.35.dist-info/entry_points.txt
batou_ext-2.4.35.dist-info/top_level.txt
batou_ext-2.4.35.dist-info/RECORD
