Metadata-Version: 2.4
Name: batou_ext
Version: 2.4.35
Summary: A library of components for batou.
Home-page: https://github.com/flyingcircusio/batou_ext
Author: Flying Circus <support@flyingcircus.io>
Author-email: support@flyingcircus.io
License: BSD (2-clause)
Keywords: deployment
Classifier: License :: OSI Approved :: BSD License
Classifier: Programming Language :: Python
Classifier: Programming Language :: Python :: 3
Classifier: Programming Language :: Python :: 3 :: Only
License-File: LICENSE.txt
Requires-Dist: batou>=2.3b4
Requires-Dist: pyaml
Requires-Dist: setuptools
Requires-Dist: six
Requires-Dist: InquirerPy
Provides-Extra: test
Requires-Dist: boto3; extra == "test"
Requires-Dist: passlib>=1.7; extra == "test"
Requires-Dist: pytest; extra == "test"
Requires-Dist: pytest-mock; extra == "test"
Provides-Extra: version-select
Requires-Dist: InquirerPy; extra == "version-select"
Provides-Extra: s3-bootstrap
Requires-Dist: boto3; extra == "s3-bootstrap"
Requires-Dist: InquirerPy; extra == "s3-bootstrap"
Dynamic: author
Dynamic: author-email
Dynamic: classifier
Dynamic: description
Dynamic: description-content-type
Dynamic: home-page
Dynamic: keywords
Dynamic: license
Dynamic: license-file
Dynamic: provides-extra
Dynamic: requires-dist
Dynamic: summary
